{
  "basic_details": {
    "code": "basic_details",
    "deleted": false,
    "$resourceStrings": null,
    "$editablePropertiesBy": null,
    "flowVersion": null,
    "productConfig": false,
    "journeyIds": null,
    "name": "Basic Details",
    "type": "conditional",
    "description": null,
    "enableIf": {
      "stepStatusConditions": null,
      "actionStatusConditions": null,
      "otherConditions": null
    },
    "applicableIf": {
      "stepStatusConditions": null,
      "actionStatusConditions": null,
      "otherConditions": null
    },
    "stepLockedMessage": null,
    "mappedState": "absli_bp7m6i-recruitment_leads_124r3a_agent_recruitment_application",
    "definitionOfDone": {
      "stepStatusConditions": null,
      "actionStatusConditions": null,
      "otherConditions": null
    },
    "reentryCriteria": null
  },
  "urn_generation": {
    "code": "urn_generation",
    "deleted": false,
    "$resourceStrings": null,
    "$editablePropertiesBy": null,
    "flowVersion": null,
    "productConfig": false,
    "journeyIds": null,
    "name": "URN Generation",
    "type": "conditional",
    "description": null,
    "enableIf": {
      "stepStatusConditions": null,
      "actionStatusConditions": null,
      "otherConditions": null
    },
    "applicableIf": {
      "stepStatusConditions": null,
      "actionStatusConditions": null,
      "otherConditions": [
        {
          "type": "standard",
          "inputs": [
            {
              "type": "value",
              "value": {
                "valType": "function",
                "operator": null,
                "operatorRequired": false,
                "function": {
                  "type": "standard",
                  "inputs": [
                    {
                      "type": "value",
                      "value": {
                        "valType": "context-standard-dimension",
                        "operator": null,
                        "operatorRequired": false,
                        "contextPath": {
                          "type": "nested",
                          "path": "steps.bm_review",
                          "dataType": "vo"
                        },
                        "standardDimension": "status"
                      }
                    },
                    {
                      "type": "value",
                      "value": {
                        "valType": "static",
                        "operator": null,
                        "operatorRequired": false,
                        "value": "COMPLETED",
                        "dataType": "text"
                      }
                    }
                  ],
                  "standardFunction": "EQUALS_IGNORE_CASE",
                  "output": null,
                  "returnType": "bool"
                }
              }
            },
            {
              "type": "value",
              "value": {
                "valType": "function",
                "operator": null,
                "operatorRequired": false,
                "function": {
                  "type": "standard",
                  "inputs": [
                    {
                      "type": "value",
                      "value": {
                        "valType": "form",
                        "operator": null,
                        "operatorRequired": false,
                        "attribute": "inputs_map.li_application_type",
                        "inputField": null
                      }
                    },
                    {
                      "type": "value",
                      "value": {
                        "valType": "static",
                        "operator": null,
                        "operatorRequired": false,
                        "value": [
                          "fresh",
                          "composite"
                        ],
                        "dataType": "text"
                      }
                    }
                  ],
                  "standardFunction": "IN",
                  "output": null,
                  "returnType": "bool"
                }
              }
            }
          ],
          "standardFunction": "AND",
          "output": null,
          "returnType": "bool"
        }
      ]
    },
    "stepLockedMessage": null,
    "mappedState": "absli_bp7m6i-recruitment_leads_124r3a_agent_recruitment_onboarding",
    "definitionOfDone": {
      "stepStatusConditions": null,
      "actionStatusConditions": [
        {
          "type": "standard",
          "inputs": [
            {
              "type": "value",
              "value": {
                "valType": "context-standard-dimension",
                "operator": null,
                "operatorRequired": false,
                "contextPath": {
                  "type": "nested",
                  "path": "step_actions.urn_generation",
                  "dataType": "vo"
                },
                "standardDimension": "status"
              }
            },
            {
              "type": "value",
              "value": {
                "valType": "static",
                "operator": null,
                "operatorRequired": false,
                "value": "COMPLETED",
                "dataType": "text"
              }
            }
          ],
          "standardFunction": "EQUALS_IGNORE_CASE",
          "output": null,
          "returnType": "bool"
        }
      ],
      "otherConditions": null
    },
    "reentryCriteria": null
  },
  "agent_code_generation": {
    "code": "agent_code_generation",
    "deleted": false,
    "$resourceStrings": null,
    "$editablePropertiesBy": null,
    "flowVersion": null,
    "productConfig": false,
    "journeyIds": null,
    "name": "Agent Code Generation",
    "type": "conditional",
    "description": null,
    "enableIf": {
      "stepStatusConditions": null,
      "actionStatusConditions": null,
      "otherConditions": null
    },
    "applicableIf": {
      "stepStatusConditions": null,
      "actionStatusConditions": null,
      "otherConditions": [
        {
          "type": "standard",
          "inputs": [
            {
              "type": "value",
              "value": {
                "valType": "function",
                "operator": null,
                "operatorRequired": false,
                "function": {
                  "type": "standard",
                  "inputs": [
                    {
                      "type": "value",
                      "value": {
                        "valType": "function",
                        "operator": null,
                        "operatorRequired": false,
                        "function": {
                          "type": "standard",
                          "inputs": [
                            {
                              "type": "value",
                              "value": {
                                "valType": "form",
                                "operator": null,
                                "operatorRequired": false,
                                "attribute": "inputs_map.li_application_type",
                                "inputField": null
                              }
                            },
                            {
                              "type": "value",
                              "value": {
                                "valType": "static",
                                "operator": null,
                                "operatorRequired": false,
                                "value": [
                                  "fresh",
                                  "composite"
                                ],
                                "dataType": "text"
                              }
                            }
                          ],
                          "standardFunction": "IN",
                          "output": null,
                          "returnType": "bool"
                        }
                      }
                    },
                    {
                      "type": "value",
                      "value": {
                        "valType": "function",
                        "operator": null,
                        "operatorRequired": false,
                        "function": {
                          "type": "standard",
                          "inputs": [
                            {
                              "type": "value",
                              "value": {
                                "valType": "context-standard-dimension",
                                "operator": null,
                                "operatorRequired": false,
                                "contextPath": {
                                  "type": "nested",
                                  "path": "steps.exam",
                                  "dataType": "vo"
                                },
                                "standardDimension": "status"
                              }
                            },
                            {
                              "type": "value",
                              "value": {
                                "valType": "static",
                                "operator": null,
                                "operatorRequired": false,
                                "value": "COMPLETED",
                                "dataType": "text"
                              }
                            }
                          ],
                          "standardFunction": "EQUALS_IGNORE_CASE",
                          "output": null,
                          "returnType": "bool"
                        }
                      }
                    }
                  ],
                  "standardFunction": "AND",
                  "output": null,
                  "returnType": "bool"
                }
              }
            },
            {
              "type": "value",
              "value": {
                "valType": "function",
                "operator": null,
                "operatorRequired": false,
                "function": {
                  "type": "standard",
                  "inputs": [
                    {
                      "type": "value",
                      "value": {
                        "valType": "function",
                        "operator": null,
                        "operatorRequired": false,
                        "function": {
                          "type": "standard",
                          "inputs": [
                            {
                              "type": "value",
                              "value": {
                                "valType": "form",
                                "operator": null,
                                "operatorRequired": false,
                                "attribute": "inputs_map.li_application_type",
                                "inputField": null
                              }
                            },
                            {
                              "type": "value",
                              "value": {
                                "valType": "static",
                                "operator": null,
                                "operatorRequired": false,
                                "value": [
                                  "transfer"
                                ],
                                "dataType": "text"
                              }
                            }
                          ],
                          "standardFunction": "IN",
                          "output": null,
                          "returnType": "bool"
                        }
                      }
                    },
                    {
                      "type": "value",
                      "value": {
                        "valType": "function",
                        "operator": null,
                        "operatorRequired": false,
                        "function": {
                          "type": "standard",
                          "inputs": [
                            {
                              "type": "value",
                              "value": {
                                "valType": "context-standard-dimension",
                                "operator": null,
                                "operatorRequired": false,
                                "contextPath": {
                                  "type": "nested",
                                  "path": "steps.bm_review",
                                  "dataType": "vo"
                                },
                                "standardDimension": "status"
                              }
                            },
                            {
                              "type": "value",
                              "value": {
                                "valType": "static",
                                "operator": null,
                                "operatorRequired": false,
                                "value": "COMPLETED",
                                "dataType": "text"
                              }
                            }
                          ],
                          "standardFunction": "EQUALS_IGNORE_CASE",
                          "output": null,
                          "returnType": "bool"
                        }
                      }
                    }
                  ],
                  "standardFunction": "AND",
                  "output": null,
                  "returnType": "bool"
                }
              }
            }
          ],
          "standardFunction": "OR",
          "output": null,
          "returnType": "bool"
        }
      ]
    },
    "stepLockedMessage": null,
    "mappedState": "absli_bp7m6i-recruitment_leads_124r3a_agent_recruitment_onboarding",
    "definitionOfDone": {
      "stepStatusConditions": null,
      "actionStatusConditions": null,
      "otherConditions": [
        {
          "type": "standard",
          "inputs": [
            {
              "type": "value",
              "value": {
                "valType": "vo",
                "operator": null,
                "operatorRequired": false,
                "attribute": "inputs_map.agent_code",
                "inputField": "inputs_map.agent_code",
                "voId": null
              }
            }
          ],
          "standardFunction": "IS_NOT_EMPTY",
          "output": null,
          "returnType": "bool"
        }
      ]
    },
    "reentryCriteria": null
  },
  "bank_details": {
    "code": "bank_details",
    "deleted": false,
    "$resourceStrings": null,
    "$editablePropertiesBy": null,
    "flowVersion": null,
    "productConfig": false,
    "journeyIds": null,
    "name": "Bank Details",
    "type": "conditional",
    "description": null,
    "enableIf": {
      "stepStatusConditions": null,
      "actionStatusConditions": [
        {
          "type": "standard",
          "inputs": [
            {
              "type": "value",
              "value": {
                "valType": "context-standard-dimension",
                "operator": null,
                "operatorRequired": false,
                "contextPath": {
                  "type": "nested",
                  "path": "step_actions.recruitment_consent",
                  "dataType": "vo"
                },
                "standardDimension": "status"
              }
            },
            {
              "type": "value",
              "value": {
                "valType": "static",
                "operator": null,
                "operatorRequired": false,
                "value": "COMPLETED",
                "dataType": "text"
              }
            }
          ],
          "standardFunction": "EQUALS_IGNORE_CASE",
          "output": null,
          "returnType": "bool"
        }
      ],
      "otherConditions": null
    },
    "applicableIf": {
      "stepStatusConditions": null,
      "actionStatusConditions": null,
      "otherConditions": null
    },
    "stepLockedMessage": null,
    "mappedState": "absli_bp7m6i-recruitment_leads_124r3a_agent_recruitment_application",
    "definitionOfDone": {
      "stepStatusConditions": null,
      "actionStatusConditions": null,
      "otherConditions": [
        {
          "type": "standard",
          "inputs": [
            {
              "type": "value",
              "value": {
                "valType": "function",
                "operator": null,
                "operatorRequired": false,
                "function": {
                  "type": "standard",
                  "inputs": [
                    {
                      "type": "value",
                      "value": {
                        "valType": "context-standard-dimension",
                        "operator": null,
                        "operatorRequired": false,
                        "contextPath": {
                          "type": "nested",
                          "path": "step_actions.validate_bank_account",
                          "dataType": "vo"
                        },
                        "standardDimension": "status"
                      }
                    },
                    {
                      "type": "value",
                      "value": {
                        "valType": "static",
                        "operator": null,
                        "operatorRequired": false,
                        "value": "COMPLETED",
                        "dataType": "text"
                      }
                    }
                  ],
                  "standardFunction": "EQUALS_IGNORE_CASE",
                  "output": null,
                  "returnType": "bool"
                }
              }
            },
            {
              "type": "value",
              "value": {
                "valType": "function",
                "operator": null,
                "operatorRequired": false,
                "function": {
                  "type": "standard",
                  "inputs": [
                    {
                      "type": "value",
                      "value": {
                        "valType": "context-standard-dimension",
                        "operator": null,
                        "operatorRequired": false,
                        "contextPath": {
                          "type": "nested",
                          "path": "step_actions.validate_bank_account",
                          "dataType": "vo"
                        },
                        "standardDimension": "status"
                      }
                    },
                    {
                      "type": "value",
                      "value": {
                        "valType": "static",
                        "operator": null,
                        "operatorRequired": false,
                        "value": "FAILED",
                        "dataType": "text"
                      }
                    }
                  ],
                  "standardFunction": "EQUALS_IGNORE_CASE",
                  "output": null,
                  "returnType": "bool"
                }
              }
            }
          ],
          "standardFunction": "OR",
          "output": null,
          "returnType": "bool"
        }
      ]
    },
    "reentryCriteria": null
  },
  "training": {
    "code": "training",
    "deleted": false,
    "$resourceStrings": null,
    "$editablePropertiesBy": null,
    "flowVersion": null,
    "productConfig": false,
    "journeyIds": null,
    "name": "Training",
    "type": "conditional",
    "description": null,
    "enableIf": {
      "stepStatusConditions": null,
      "actionStatusConditions": null,
      "otherConditions": null
    },
    "applicableIf": {
      "stepStatusConditions": null,
      "actionStatusConditions": null,
      "otherConditions": [
        {
          "type": "standard",
          "inputs": [
            {
              "type": "value",
              "value": {
                "valType": "function",
                "operator": null,
                "operatorRequired": false,
                "function": {
                  "type": "standard",
                  "inputs": [
                    {
                      "type": "value",
                      "value": {
                        "valType": "function",
                        "operator": null,
                        "operatorRequired": false,
                        "function": {
                          "type": "standard",
                          "inputs": [
                            {
                              "type": "value",
                              "value": {
                                "valType": "form",
                                "operator": null,
                                "operatorRequired": false,
                                "attribute": "inputs_map.li_application_type",
                                "inputField": null
                              }
                            },
                            {
                              "type": "value",
                              "value": {
                                "valType": "static",
                                "operator": null,
                                "operatorRequired": false,
                                "value": [
                                  "fresh",
                                  "composite"
                                ],
                                "dataType": "text"
                              }
                            }
                          ],
                          "standardFunction": "IN",
                          "output": null,
                          "returnType": "bool"
                        }
                      }
                    },
                    {
                      "type": "value",
                      "value": {
                        "valType": "function",
                        "operator": null,
                        "operatorRequired": false,
                        "function": {
                          "type": "standard",
                          "inputs": [
                            {
                              "type": "value",
                              "value": {
                                "valType": "context-standard-dimension",
                                "operator": null,
                                "operatorRequired": false,
                                "contextPath": {
                                  "type": "nested",
                                  "path": "steps.urn_generation",
                                  "dataType": "vo"
                                },
                                "standardDimension": "status"
                              }
                            },
                            {
                              "type": "value",
                              "value": {
                                "valType": "static",
                                "operator": null,
                                "operatorRequired": false,
                                "value": "COMPLETED",
                                "dataType": "text"
                              }
                            }
                          ],
                          "standardFunction": "EQUALS_IGNORE_CASE",
                          "output": null,
                          "returnType": "bool"
                        }
                      }
                    }
                  ],
                  "standardFunction": "AND",
                  "output": null,
                  "returnType": "bool"
                }
              }
            },
            {
              "type": "value",
              "value": {
                "valType": "function",
                "operator": null,
                "operatorRequired": false,
                "function": {
                  "type": "standard",
                  "inputs": [
                    {
                      "type": "value",
                      "value": {
                        "valType": "function",
                        "operator": null,
                        "operatorRequired": false,
                        "function": {
                          "type": "standard",
                          "inputs": [
                            {
                              "type": "value",
                              "value": {
                                "valType": "form",
                                "operator": null,
                                "operatorRequired": false,
                                "attribute": "inputs_map.li_application_type",
                                "inputField": null
                              }
                            },
                            {
                              "type": "value",
                              "value": {
                                "valType": "static",
                                "operator": null,
                                "operatorRequired": false,
                                "value": [
                                  "posp"
                                ],
                                "dataType": "text"
                              }
                            }
                          ],
                          "standardFunction": "IN",
                          "output": null,
                          "returnType": "bool"
                        }
                      }
                    },
                    {
                      "type": "value",
                      "value": {
                        "valType": "function",
                        "operator": null,
                        "operatorRequired": false,
                        "function": {
                          "type": "standard",
                          "inputs": [
                            {
                              "type": "value",
                              "value": {
                                "valType": "context-standard-dimension",
                                "operator": null,
                                "operatorRequired": false,
                                "contextPath": {
                                  "type": "nested",
                                  "path": "steps.bm_review",
                                  "dataType": "vo"
                                },
                                "standardDimension": "status"
                              }
                            },
                            {
                              "type": "value",
                              "value": {
                                "valType": "static",
                                "operator": null,
                                "operatorRequired": false,
                                "value": "COMPLETED",
                                "dataType": "text"
                              }
                            }
                          ],
                          "standardFunction": "EQUALS_IGNORE_CASE",
                          "output": null,
                          "returnType": "bool"
                        }
                      }
                    }
                  ],
                  "standardFunction": "AND",
                  "output": null,
                  "returnType": "bool"
                }
              }
            }
          ],
          "standardFunction": "OR",
          "output": null,
          "returnType": "bool"
        }
      ]
    },
    "stepLockedMessage": null,
    "mappedState": "absli_bp7m6i-recruitment_leads_124r3a_agent_recruitment_onboarding",
    "definitionOfDone": {
      "stepStatusConditions": null,
      "actionStatusConditions": null,
      "otherConditions": [
        {
          "type": "standard",
          "inputs": [
            {
              "type": "value",
              "value": {
                "valType": "function",
                "operator": null,
                "operatorRequired": false,
                "function": {
                  "type": "standard",
                  "inputs": [
                    {
                      "type": "value",
                      "value": {
                        "valType": "context-standard-dimension",
                        "operator": null,
                        "operatorRequired": false,
                        "contextPath": {
                          "type": "nested",
                          "path": "step_actions.training_schedule",
                          "dataType": "vo"
                        },
                        "standardDimension": "status"
                      }
                    },
                    {
                      "type": "value",
                      "value": {
                        "valType": "static",
                        "operator": null,
                        "operatorRequired": false,
                        "value": "COMPLETED",
                        "dataType": "text"
                      }
                    }
                  ],
                  "standardFunction": "EQUALS_IGNORE_CASE",
                  "output": null,
                  "returnType": "bool"
                }
              }
            },
            {
              "type": "value",
              "value": {
                "valType": "function",
                "operator": null,
                "operatorRequired": false,
                "function": {
                  "type": "standard",
                  "inputs": [
                    {
                      "type": "value",
                      "value": {
                        "valType": "context-standard-dimension",
                        "operator": null,
                        "operatorRequired": false,
                        "contextPath": {
                          "type": "nested",
                          "path": "step_actions.posp_training",
                          "dataType": "vo"
                        },
                        "standardDimension": "status"
                      }
                    },
                    {
                      "type": "value",
                      "value": {
                        "valType": "static",
                        "operator": null,
                        "operatorRequired": false,
                        "value": "COMPLETED",
                        "dataType": "text"
                      }
                    }
                  ],
                  "standardFunction": "EQUALS_IGNORE_CASE",
                  "output": null,
                  "returnType": "bool"
                }
              }
            }
          ],
          "standardFunction": "OR",
          "output": null,
          "returnType": "bool"
        }
      ]
    },
    "reentryCriteria": null
  },
  "absli_bp7m6i-recruitment_leads_124r3a_posp_code_generation": {
    "code": "absli_bp7m6i-recruitment_leads_124r3a_posp_code_generation",
    "deleted": false,
    "$resourceStrings": null,
    "$editablePropertiesBy": null,
    "flowVersion": null,
    "productConfig": false,
    "journeyIds": null,
    "name": "POSP Code Generation",
    "type": "conditional",
    "description": null,
    "enableIf": {
      "stepStatusConditions": null,
      "actionStatusConditions": null,
      "otherConditions": null
    },
    "applicableIf": {
      "stepStatusConditions": null,
      "actionStatusConditions": null,
      "otherConditions": [
        {
          "type": "standard",
          "inputs": [
            {
              "type": "value",
              "value": {
                "valType": "function",
                "operator": null,
                "operatorRequired": false,
                "function": {
                  "type": "standard",
                  "inputs": [
                    {
                      "type": "value",
                      "value": {
                        "valType": "context-standard-dimension",
                        "operator": null,
                        "operatorRequired": false,
                        "contextPath": {
                          "type": "nested",
                          "path": "steps.mock_exam_internal",
                          "dataType": "vo"
                        },
                        "standardDimension": "status"
                      }
                    },
                    {
                      "type": "value",
                      "value": {
                        "valType": "static",
                        "operator": null,
                        "operatorRequired": false,
                        "value": "COMPLETED",
                        "dataType": "text"
                      }
                    }
                  ],
                  "standardFunction": "EQUALS_IGNORE_CASE",
                  "output": null,
                  "returnType": "bool"
                }
              }
            },
            {
              "type": "value",
              "value": {
                "valType": "function",
                "operator": null,
                "operatorRequired": false,
                "function": {
                  "type": "standard",
                  "inputs": [
                    {
                      "type": "value",
                      "value": {
                        "valType": "vo",
                        "operator": null,
                        "operatorRequired": false,
                        "attribute": "inputs_map.li_application_type",
                        "inputField": null,
                        "voId": null
                      }
                    },
                    {
                      "type": "value",
                      "value": {
                        "valType": "static",
                        "operator": null,
                        "operatorRequired": false,
                        "value": [
                          "posp"
                        ],
                        "dataType": "text"
                      }
                    }
                  ],
                  "standardFunction": "IN",
                  "output": null,
                  "returnType": "bool"
                }
              }
            }
          ],
          "standardFunction": "AND",
          "output": null,
          "returnType": "bool"
        }
      ]
    },
    "stepLockedMessage": null,
    "mappedState": "absli_bp7m6i-recruitment_leads_124r3a_agent_recruitment_onboarding",
    "definitionOfDone": {
      "stepStatusConditions": null,
      "actionStatusConditions": null,
      "otherConditions": [
        {
          "type": "standard",
          "inputs": [
            {
              "type": "value",
              "value": {
                "valType": "vo",
                "operator": null,
                "operatorRequired": false,
                "attribute": "inputs_map.agent_code",
                "inputField": "inputs_map.agent_code",
                "voId": null
              }
            }
          ],
          "standardFunction": "IS_NOT_EMPTY",
          "output": null,
          "returnType": "bool"
        }
      ]
    },
    "reentryCriteria": null
  },
  "mock_exam_internal": {
    "code": "mock_exam_internal",
    "deleted": false,
    "$resourceStrings": null,
    "$editablePropertiesBy": null,
    "flowVersion": null,
    "productConfig": false,
    "journeyIds": null,
    "name": "Mock Exam",
    "type": "conditional",
    "description": null,
    "enableIf": {
      "stepStatusConditions": null,
      "actionStatusConditions": null,
      "otherConditions": null
    },
    "applicableIf": {
      "stepStatusConditions": null,
      "actionStatusConditions": null,
      "otherConditions": [
        {
          "type": "standard",
          "inputs": [
            {
              "type": "value",
              "value": {
                "valType": "function",
                "operator": null,
                "operatorRequired": false,
                "function": {
                  "type": "standard",
                  "inputs": [
                    {
                      "type": "value",
                      "value": {
                        "valType": "context-standard-dimension",
                        "operator": null,
                        "operatorRequired": false,
                        "contextPath": {
                          "type": "nested",
                          "path": "steps.training",
                          "dataType": "vo"
                        },
                        "standardDimension": "status"
                      }
                    },
                    {
                      "type": "value",
                      "value": {
                        "valType": "static",
                        "operator": null,
                        "operatorRequired": false,
                        "value": "COMPLETED",
                        "dataType": "text"
                      }
                    }
                  ],
                  "standardFunction": "EQUALS_IGNORE_CASE",
                  "output": null,
                  "returnType": "bool"
                }
              }
            },
            {
              "type": "value",
              "value": {
                "valType": "function",
                "operator": null,
                "operatorRequired": false,
                "function": {
                  "type": "standard",
                  "inputs": [
                    {
                      "type": "value",
                      "value": {
                        "valType": "vo",
                        "operator": null,
                        "operatorRequired": false,
                        "attribute": "inputs_map.li_application_type",
                        "inputField": null,
                        "voId": null
                      }
                    },
                    {
                      "type": "value",
                      "value": {
                        "valType": "static",
                        "operator": null,
                        "operatorRequired": false,
                        "value": [
                          "posp"
                        ],
                        "dataType": "text"
                      }
                    }
                  ],
                  "standardFunction": "IN",
                  "output": null,
                  "returnType": "bool"
                }
              }
            }
          ],
          "standardFunction": "AND",
          "output": null,
          "returnType": "bool"
        }
      ]
    },
    "stepLockedMessage": null,
    "mappedState": "absli_bp7m6i-recruitment_leads_124r3a_agent_recruitment_onboarding",
    "definitionOfDone": {
      "stepStatusConditions": null,
      "actionStatusConditions": null,
      "otherConditions": null
    },
    "reentryCriteria": null
  },
  "additional_details": {
    "code": "additional_details",
    "deleted": false,
    "$resourceStrings": null,
    "$editablePropertiesBy": null,
    "flowVersion": null,
    "productConfig": false,
    "journeyIds": null,
    "name": "Additional Details",
    "type": "conditional",
    "description": null,
    "enableIf": {
      "stepStatusConditions": null,
      "actionStatusConditions": [
        {
          "type": "standard",
          "inputs": [
            {
              "type": "value",
              "value": {
                "valType": "context-standard-dimension",
                "operator": null,
                "operatorRequired": false,
                "contextPath": {
                  "type": "nested",
                  "path": "step_actions.recruitment_consent",
                  "dataType": "vo"
                },
                "standardDimension": "status"
              }
            },
            {
              "type": "value",
              "value": {
                "valType": "static",
                "operator": null,
                "operatorRequired": false,
                "value": "COMPLETED",
                "dataType": "text"
              }
            }
          ],
          "standardFunction": "EQUALS_IGNORE_CASE",
          "output": null,
          "returnType": "bool"
        }
      ],
      "otherConditions": null
    },
    "applicableIf": {
      "stepStatusConditions": null,
      "actionStatusConditions": null,
      "otherConditions": null
    },
    "stepLockedMessage": null,
    "mappedState": "absli_bp7m6i-recruitment_leads_124r3a_agent_recruitment_application",
    "definitionOfDone": {
      "stepStatusConditions": null,
      "actionStatusConditions": null,
      "otherConditions": null
    },
    "reentryCriteria": null
  },
  "bm_review": {
    "code": "bm_review",
    "deleted": false,
    "$resourceStrings": null,
    "$editablePropertiesBy": null,
    "flowVersion": null,
    "productConfig": false,
    "journeyIds": null,
    "name": "Branch Manager Review",
    "type": "conditional",
    "description": null,
    "enableIf": {
      "stepStatusConditions": [
        {
          "type": "standard",
          "inputs": [
            {
              "type": "value",
              "value": {
                "valType": "context-standard-dimension",
                "operator": null,
                "operatorRequired": false,
                "contextPath": {
                  "type": "nested",
                  "path": "steps.application_submission",
                  "dataType": "vo"
                },
                "standardDimension": "status"
              }
            },
            {
              "type": "value",
              "value": {
                "valType": "static",
                "operator": null,
                "operatorRequired": false,
                "value": "COMPLETED",
                "dataType": "text"
              }
            }
          ],
          "standardFunction": "EQUALS_IGNORE_CASE",
          "output": null,
          "returnType": "bool"
        }
      ],
      "actionStatusConditions": null,
      "otherConditions": null
    },
    "applicableIf": {
      "stepStatusConditions": null,
      "actionStatusConditions": null,
      "otherConditions": [
        {
          "type": "standard",
          "inputs": [
            {
              "type": "value",
              "value": {
                "valType": "function",
                "operator": null,
                "operatorRequired": false,
                "function": {
                  "type": "standard",
                  "inputs": [
                    {
                      "type": "value",
                      "value": {
                        "valType": "vo",
                        "operator": null,
                        "operatorRequired": false,
                        "attribute": "inputs_map.insurance_distributor_type",
                        "inputField": "inputs_map.insurance_distributor_type",
                        "voId": null
                      }
                    },
                    {
                      "type": "value",
                      "value": {
                        "valType": "static",
                        "operator": null,
                        "operatorRequired": false,
                        "value": "Partner Office",
                        "dataType": "text"
                      }
                    }
                  ],
                  "standardFunction": "NOT_EQUALS",
                  "output": null,
                  "returnType": "bool"
                }
              }
            },
            {
              "type": "value",
              "value": {
                "valType": "function",
                "operator": null,
                "operatorRequired": false,
                "function": {
                  "type": "standard",
                  "inputs": [
                    {
                      "type": "value",
                      "value": {
                        "valType": "vo",
                        "operator": null,
                        "operatorRequired": false,
                        "attribute": "inputs_map.insurance_distributor_type",
                        "inputField": "inputs_map.insurance_distributor_type",
                        "voId": null
                      }
                    }
                  ],
                  "standardFunction": "IS_EMPTY",
                  "output": null,
                  "returnType": "bool"
                }
              }
            }
          ],
          "standardFunction": "OR",
          "output": null,
          "returnType": "bool"
        }
      ]
    },
    "stepLockedMessage": null,
    "mappedState": "absli_bp7m6i-recruitment_leads_124r3a_agent_recruitment_onboarding",
    "definitionOfDone": {
      "stepStatusConditions": null,
      "actionStatusConditions": null,
      "otherConditions": null
    },
    "reentryCriteria": null
  },
  "exam": {
    "code": "exam",
    "deleted": false,
    "$resourceStrings": null,
    "$editablePropertiesBy": null,
    "flowVersion": null,
    "productConfig": false,
    "journeyIds": null,
    "name": "IRDAI Exam",
    "type": "conditional",
    "description": null,
    "enableIf": {
      "stepStatusConditions": null,
      "actionStatusConditions": null,
      "otherConditions": [
        {
          "type": "standard",
          "inputs": [
            {
              "type": "value",
              "value": {
                "valType": "function",
                "operator": null,
                "operatorRequired": false,
                "function": {
                  "type": "standard",
                  "inputs": [
                    {
                      "type": "value",
                      "value": {
                        "valType": "context-standard-dimension",
                        "operator": null,
                        "operatorRequired": false,
                        "contextPath": {
                          "type": "nested",
                          "path": "steps.mock_exam_internal",
                          "dataType": "vo"
                        },
                        "standardDimension": "status"
                      }
                    },
                    {
                      "type": "value",
                      "value": {
                        "valType": "static",
                        "operator": null,
                        "operatorRequired": false,
                        "value": "COMPLETED",
                        "dataType": "text"
                      }
                    }
                  ],
                  "standardFunction": "EQUALS_IGNORE_CASE",
                  "output": null,
                  "returnType": "bool"
                }
              }
            },
            {
              "type": "value",
              "value": {
                "valType": "function",
                "operator": null,
                "operatorRequired": false,
                "function": {
                  "type": "standard",
                  "inputs": [
                    {
                      "type": "value",
                      "value": {
                        "valType": "context-standard-dimension",
                        "operator": null,
                        "operatorRequired": false,
                        "contextPath": {
                          "type": "nested",
                          "path": "step_actions.training_schedule",
                          "dataType": "vo"
                        },
                        "standardDimension": "status"
                      }
                    },
                    {
                      "type": "value",
                      "value": {
                        "valType": "static",
                        "operator": null,
                        "operatorRequired": false,
                        "value": "COMPLETED",
                        "dataType": "text"
                      }
                    }
                  ],
                  "standardFunction": "EQUALS_IGNORE_CASE",
                  "output": null,
                  "returnType": "bool"
                }
              }
            }
          ],
          "standardFunction": "OR",
          "output": null,
          "returnType": "bool"
        }
      ]
    },
    "applicableIf": {
      "stepStatusConditions": null,
      "actionStatusConditions": null,
      "otherConditions": [
        {
          "type": "standard",
          "inputs": [
            {
              "type": "value",
              "value": {
                "valType": "function",
                "operator": null,
                "operatorRequired": false,
                "function": {
                  "type": "standard",
                  "inputs": [
                    {
                      "type": "value",
                      "value": {
                        "valType": "context-standard-dimension",
                        "operator": null,
                        "operatorRequired": false,
                        "contextPath": {
                          "type": "nested",
                          "path": "step_actions.training_schedule",
                          "dataType": "vo"
                        },
                        "standardDimension": "status"
                      }
                    },
                    {
                      "type": "value",
                      "value": {
                        "valType": "static",
                        "operator": null,
                        "operatorRequired": false,
                        "value": "COMPLETED",
                        "dataType": "text"
                      }
                    }
                  ],
                  "standardFunction": "EQUALS_IGNORE_CASE",
                  "output": null,
                  "returnType": "bool"
                }
              }
            },
            {
              "type": "value",
              "value": {
                "valType": "function",
                "operator": null,
                "operatorRequired": false,
                "function": {
                  "type": "standard",
                  "inputs": [
                    {
                      "type": "value",
                      "value": {
                        "valType": "vo",
                        "operator": null,
                        "operatorRequired": false,
                        "attribute": "inputs_map.li_application_type",
                        "inputField": null,
                        "voId": null
                      }
                    },
                    {
                      "type": "value",
                      "value": {
                        "valType": "static",
                        "operator": null,
                        "operatorRequired": false,
                        "value": [
                          "fresh",
                          "composite"
                        ],
                        "dataType": "text"
                      }
                    }
                  ],
                  "standardFunction": "IN",
                  "output": null,
                  "returnType": "bool"
                }
              }
            }
          ],
          "standardFunction": "AND",
          "output": null,
          "returnType": "bool"
        }
      ]
    },
    "stepLockedMessage": null,
    "mappedState": "absli_bp7m6i-recruitment_leads_124r3a_agent_recruitment_onboarding",
    "definitionOfDone": {
      "stepStatusConditions": null,
      "actionStatusConditions": null,
      "otherConditions": [
        {
          "type": "standard",
          "inputs": [
            {
              "type": "value",
              "value": {
                "valType": "form",
                "operator": null,
                "operatorRequired": false,
                "attribute": "inputs_map.exam_outcome",
                "inputField": null
              }
            },
            {
              "type": "value",
              "value": {
                "valType": "static",
                "operator": null,
                "operatorRequired": false,
                "value": "Pass",
                "dataType": "text"
              }
            }
          ],
          "standardFunction": "EQUALS_IGNORE_CASE",
          "output": null,
          "returnType": "bool"
        }
      ]
    },
    "reentryCriteria": {
      "stepStatusConditions": null,
      "actionStatusConditions": null,
      "otherConditions": [
        {
          "type": "standard",
          "inputs": [
            {
              "type": "value",
              "value": {
                "valType": "vo",
                "operator": null,
                "operatorRequired": false,
                "attribute": "inputs_map._exam_outcome",
                "inputField": "inputs_map._exam_outcome",
                "voId": null
              }
            },
            {
              "type": "value",
              "value": {
                "valType": "static",
                "operator": null,
                "operatorRequired": false,
                "value": [
                  "Fail",
                  "Absent"
                ],
                "dataType": "list"
              }
            }
          ],
          "standardFunction": "IN",
          "output": null,
          "returnType": "bool"
        }
      ]
    }
  },
  "posp_training": {
    "code": "posp_training",
    "deleted": true,
    "$resourceStrings": null,
    "$editablePropertiesBy": null,
    "flowVersion": null,
    "productConfig": false,
    "journeyIds": null,
    "name": "POSP Training",
    "type": "conditional",
    "description": null,
    "enableIf": {
      "stepStatusConditions": null,
      "actionStatusConditions": null,
      "otherConditions": null
    },
    "applicableIf": {
      "stepStatusConditions": null,
      "actionStatusConditions": null,
      "otherConditions": null
    },
    "stepLockedMessage": null,
    "mappedState": "absli_bp7m6i-recruitment_leads_124r3a_agent_recruitment_onboarding",
    "definitionOfDone": {
      "stepStatusConditions": null,
      "actionStatusConditions": null,
      "otherConditions": null
    },
    "reentryCriteria": null
  },
  "kyc": {
    "code": "kyc",
    "deleted": false,
    "$resourceStrings": null,
    "$editablePropertiesBy": null,
    "flowVersion": null,
    "productConfig": false,
    "journeyIds": null,
    "name": "KYC Verification",
    "type": "conditional",
    "description": null,
    "enableIf": {
      "stepStatusConditions": null,
      "actionStatusConditions": [
        {
          "type": "standard",
          "inputs": [
            {
              "type": "value",
              "value": {
                "valType": "context-standard-dimension",
                "operator": null,
                "operatorRequired": false,
                "contextPath": {
                  "type": "nested",
                  "path": "step_actions.recruitment_consent",
                  "dataType": "vo"
                },
                "standardDimension": "status"
              }
            },
            {
              "type": "value",
              "value": {
                "valType": "static",
                "operator": null,
                "operatorRequired": false,
                "value": "COMPLETED",
                "dataType": "text"
              }
            }
          ],
          "standardFunction": "EQUALS_IGNORE_CASE",
          "output": null,
          "returnType": "bool"
        }
      ],
      "otherConditions": null
    },
    "applicableIf": {
      "stepStatusConditions": null,
      "actionStatusConditions": null,
      "otherConditions": null
    },
    "stepLockedMessage": null,
    "mappedState": "absli_bp7m6i-recruitment_leads_124r3a_agent_recruitment_application",
    "definitionOfDone": {
      "stepStatusConditions": null,
      "actionStatusConditions": null,
      "otherConditions": [
        {
          "type": "standard",
          "inputs": [
            {
              "type": "value",
              "value": {
                "valType": "function",
                "operator": null,
                "operatorRequired": false,
                "function": {
                  "type": "standard",
                  "inputs": [
                    {
                      "type": "value",
                      "value": {
                        "valType": "context-standard-dimension",
                        "operator": null,
                        "operatorRequired": false,
                        "contextPath": {
                          "type": "nested",
                          "path": "step_actions.ckyc",
                          "dataType": "vo"
                        },
                        "standardDimension": "status"
                      }
                    },
                    {
                      "type": "value",
                      "value": {
                        "valType": "static",
                        "operator": null,
                        "operatorRequired": false,
                        "value": "COMPLETED",
                        "dataType": "text"
                      }
                    }
                  ],
                  "standardFunction": "EQUALS_IGNORE_CASE",
                  "output": null,
                  "returnType": "bool"
                }
              }
            },
            {
              "type": "value",
              "value": {
                "valType": "function",
                "operator": null,
                "operatorRequired": false,
                "function": {
                  "type": "standard",
                  "inputs": [
                    {
                      "type": "value",
                      "value": {
                        "valType": "context-standard-dimension",
                        "operator": null,
                        "operatorRequired": false,
                        "contextPath": {
                          "type": "nested",
                          "path": "step_actions.manual_kyc",
                          "dataType": "vo"
                        },
                        "standardDimension": "status"
                      }
                    },
                    {
                      "type": "value",
                      "value": {
                        "valType": "static",
                        "operator": null,
                        "operatorRequired": false,
                        "value": "COMPLETED",
                        "dataType": "text"
                      }
                    }
                  ],
                  "standardFunction": "EQUALS_IGNORE_CASE",
                  "output": null,
                  "returnType": "bool"
                }
              }
            }
          ],
          "standardFunction": "OR",
          "output": null,
          "returnType": "bool"
        }
      ]
    },
    "reentryCriteria": null
  },
  "application_submission": {
    "code": "application_submission",
    "deleted": false,
    "$resourceStrings": null,
    "$editablePropertiesBy": null,
    "flowVersion": null,
    "productConfig": false,
    "journeyIds": null,
    "name": "Application Submission",
    "type": "conditional",
    "description": null,
    "enableIf": {
      "stepStatusConditions": [
        {
          "type": "standard",
          "inputs": [
            {
              "type": "value",
              "value": {
                "valType": "context-standard-dimension",
                "operator": null,
                "operatorRequired": false,
                "contextPath": {
                  "type": "nested",
                  "path": "steps.additional_details",
                  "dataType": "vo"
                },
                "standardDimension": "status"
              }
            },
            {
              "type": "value",
              "value": {
                "valType": "static",
                "operator": null,
                "operatorRequired": false,
                "value": "COMPLETED",
                "dataType": "text"
              }
            }
          ],
          "standardFunction": "EQUALS_IGNORE_CASE",
          "output": null,
          "returnType": "bool"
        },
        {
          "type": "standard",
          "inputs": [
            {
              "type": "value",
              "value": {
                "valType": "context-standard-dimension",
                "operator": null,
                "operatorRequired": false,
                "contextPath": {
                  "type": "nested",
                  "path": "steps.bank_details",
                  "dataType": "vo"
                },
                "standardDimension": "status"
              }
            },
            {
              "type": "value",
              "value": {
                "valType": "static",
                "operator": null,
                "operatorRequired": false,
                "value": "COMPLETED",
                "dataType": "text"
              }
            }
          ],
          "standardFunction": "EQUALS_IGNORE_CASE",
          "output": null,
          "returnType": "bool"
        },
        {
          "type": "standard",
          "inputs": [
            {
              "type": "value",
              "value": {
                "valType": "context-standard-dimension",
                "operator": null,
                "operatorRequired": false,
                "contextPath": {
                  "type": "nested",
                  "path": "steps.kyc",
                  "dataType": "vo"
                },
                "standardDimension": "status"
              }
            },
            {
              "type": "value",
              "value": {
                "valType": "static",
                "operator": null,
                "operatorRequired": false,
                "value": "COMPLETED",
                "dataType": "text"
              }
            }
          ],
          "standardFunction": "EQUALS_IGNORE_CASE",
          "output": null,
          "returnType": "bool"
        }
      ],
      "actionStatusConditions": null,
      "otherConditions": null
    },
    "applicableIf": {
      "stepStatusConditions": null,
      "actionStatusConditions": null,
      "otherConditions": null
    },
    "stepLockedMessage": null,
    "mappedState": "absli_bp7m6i-recruitment_leads_124r3a_agent_recruitment_application",
    "definitionOfDone": {
      "stepStatusConditions": null,
      "actionStatusConditions": [
        {
          "type": "standard",
          "inputs": [
            {
              "type": "value",
              "value": {
                "valType": "context-standard-dimension",
                "operator": null,
                "operatorRequired": false,
                "contextPath": {
                  "type": "nested",
                  "path": "step_actions.application_verification",
                  "dataType": "vo"
                },
                "standardDimension": "status"
              }
            },
            {
              "type": "value",
              "value": {
                "valType": "static",
                "operator": null,
                "operatorRequired": false,
                "value": "COMPLETED",
                "dataType": "text"
              }
            }
          ],
          "standardFunction": "EQUALS_IGNORE_CASE",
          "output": null,
          "returnType": "bool"
        }
      ],
      "otherConditions": null
    },
    "reentryCriteria": null
  }
}
